{"data":{"allDataJson":{"totalCount":1,"edges":[{"node":{"id":"c604238c-e5a6-5468-bd1d-eb182e27ac5c","search":{"edges":[{"node":{"name":"Landry Ngoya","login":"foxkin","databaseId":40372298,"location":"Tokyo,Kinshasa","createdAt":"2018-06-18T21:58:31Z","isHireable":false,"websiteUrl":"https://www.linkedin.com/in/landry-ngoya-1a4b4362","repositoriesContributedTo":{"edges":[]}}},{"node":{"name":null,"login":null,"databaseId":null,"location":null,"createdAt":null,"isHireable":null,"websiteUrl":null,"repositoriesContributedTo":null}},{"node":{"name":"Axel KAPITA ","login":"axelkapita","databaseId":39138929,"location":"Kinshasa","createdAt":"2018-05-09T21:24:01Z","isHireable":false,"websiteUrl":"","repositoriesContributedTo":{"edges":[{"node":{"forkCount":0,"stargazers":{"totalCount":0},"primaryLanguage":null,"nameWithOwner":"axelkapita/demo_git"}},{"node":{"forkCount":0,"stargazers":{"totalCount":0},"primaryLanguage":null,"nameWithOwner":"axelkapita/activite"}}]}}},{"node":{"name":"Black Knight","login":"brucembayo","databaseId":38949737,"location":"Kinshasa, DRC","createdAt":"2018-05-03T13:11:11Z","isHireable":false,"websiteUrl":"","repositoriesContributedTo":{"edges":[{"node":{"forkCount":0,"stargazers":{"totalCount":0},"primaryLanguage":{"name":"JavaScript"},"nameWithOwner":"brucembayo/enketo-transformer"}}]}}},{"node":{"name":"José N'Sele","login":"kingjoesoul","databaseId":38202447,"location":"Kinshasa, DRC","createdAt":"2018-04-09T06:01:07Z","isHireable":true,"websiteUrl":"kassongo@aqili.com","repositoriesContributedTo":{"edges":[{"node":{"forkCount":0,"stargazers":{"totalCount":0},"primaryLanguage":null,"nameWithOwner":"kingjoesoul/reimagined-engine"}}]}}}]}}}]}},"pageContext":{"languages":[{"value":"en","text":"English"},{"value":"fr","text":"French"}],"locale":"fr","routed":true,"originalPath":"/page-2/"}}